elo_grad/__init__.py
elo_grad/plot.py
elo_grad/py.typed
elo_grad/sklearn.py
elo_grad-0.5.1.dist-info/METADATA
elo_grad-0.5.1.dist-info/WHEEL
elo_grad-0.5.1.dist-info/licenses/LICENSE
elo_grad-0.5.1.dist-info/RECORD
