Metadata-Version: 2.4
Name: elo-grad
Version: 0.5.1
Summary: Extended Elo rating system implementation based on the equivalence with logistic regression.
Author-email: Mike Cooke <cookepm@tcd.ie>
License-File: LICENSE
Classifier: License :: OSI Approved :: Apache Software License
Classifier: Programming Language :: Python
Classifier: Programming Language :: Python :: 3
Classifier: Programming Language :: Python :: 3.10
Classifier: Programming Language :: Python :: 3.11
Classifier: Programming Language :: Python :: 3.12
Classifier: Programming Language :: Python :: 3.13
Requires-Python: >=3.10
Requires-Dist: narwhals>=1.14.0
Provides-Extra: examples
Requires-Dist: ipykernel>=6.29.5; extra == 'examples'
Requires-Dist: matplotlib>=3.9.2; extra == 'examples'
Requires-Dist: numpy>=2.1.2; extra == 'examples'
Requires-Dist: pandas>=2.2.3; extra == 'examples'
Requires-Dist: polars>=1.14.0; extra == 'examples'
Requires-Dist: scipy>=1.14.1; extra == 'examples'
Provides-Extra: plot
Requires-Dist: matplotlib>=3.9.2; extra == 'plot'
Provides-Extra: sklearn
Requires-Dist: scikit-learn>=1.5.2; extra == 'sklearn'
